projetodorotheu/__init__.py
projetodorotheu/capital_mod.py
projetodorotheu/main.py
projetodorotheu/data/cap_data.txt
projetodorotheu-0.1.1.data/scripts/cap_script.py
projetodorotheu-0.1.1.dist-info/METADATA
projetodorotheu-0.1.1.dist-info/WHEEL
projetodorotheu-0.1.1.dist-info/top_level.txt
projetodorotheu-0.1.1.dist-info/RECORD
