Metadata-Version: 2.1
Name: projetodorotheu
Version: 0.1.1
Summary: My first python project
Home-page: UNKNOWN
Author: Dorotheu
Author-email: UNKNOWN
License: MIT
Platform: UNKNOWN
